Workbook

Sheet COVER
C3: COMAPARABLE COMPANY VALUATION
C7: EV/EBITDA & P/E MULTIPLE ANALYSIS
F10: SUBMITTED By | G10: Khushi Rampal
F11: Submitted to | G11: Prof. pulin aggarwal
F12: Subject | G12: EQUITY ANALYSIS & Business Valuation
F13: Valuation Date | G13: 46234
F14: Values | G14: Represented in $US (in Millions)
G15: (Unless Specified)
F16: Companies Evaluated | G16: Microsoft
G17: Alphabet
G18: Oracle
G19: Salesforce
G20: IBM
G21: Wipro
G22: Infosys
G23: TCS

Sheet US COMPANIES
B2: US PEER COMPANIES
B6: Company | C6: Share Price (31 Jul) | D6: Market Cap | E6: EV | F6: EBITDA 2026E | G6: EBITDA 2027E | H6: EV/EBITDA 2026E | I6: EV/EBITDA 2027E | J6: P/E
B8: Microsoft | C8: 464.72 | D8: 3677000 | E8: ='EV BRIDGE'!E17 -> 3656983 | F8: =CALANDARISATION!D20 -> 274583.33 | G8: =CALANDARISATION!D21 -> 344733.33 | H8: =E8/F8 -> 13.318299 | I8: =E8/G8 -> 10.60815 | J8: 25.71
B9: Alphabet | C9: 356.13 | D9: 4230000 | E9: ='EV BRIDGE'!F17 -> 4162448 | F9: =CALANDARISATION!E20 -> 296100 | G9: =CALANDARISATION!E21 -> 382600 | H9: =E9/F9 -> 14.057575 | I9: =E9/G9 -> 10.879373 | J9: 25.32
B10: Oracle | C10: 129.87 | D10: 433569 | E10: ='EV BRIDGE'!G17 -> 563366 | F10: =CALANDARISATION!F20 -> 62485.833 | G10: =CALANDARISATION!F21 -> 89897.917 | H10: =E10/F10 -> 9.0158996 | I10: =E10/G10 -> 6.2667303 | J10: 28.17
B11: Salesforce | C11: 184.02 | D11: 160696 | E11: ='EV BRIDGE'!H17 -> 168307 | F11: =CALANDARISATION!G20 -> 18774.083 | G11: =CALANDARISATION!G21 -> 20718 | H11: =E11/F11 -> 8.9648585 | I11: =E11/G11 -> 8.1237089 | J11: 13.4
B12: IBM | C12: 223.65 | D12: 220761 | E12: ='EV BRIDGE'!I17 -> 261588 | F12: =CALANDARISATION!H20 -> 21334 | G12: =CALANDARISATION!H21 -> 22850 | H12: =E12/F12 -> 12.261554 | I12: =E12/G12 -> 11.448053 | J12: 22.73
B14: Note: Market capitalization is based on the closing share price as of 31 July 2026. Enterprise Value is derived using the EV Bridge methodology, while EBITDA forecasts are calendarized to a December year-end where applicable.

Sheet INDIAN COMPANIES
D2: US PEER COMPANIES
D6: Company | E6: Share Price (31 Jul) | F6: Market Cap | G6: EV/EBITDA 2026E | H6: EV/EBITDA 2027E | I6: P/E
D8: Wipro | E8: 1.98 | F8: 19192 | G8: 8.9 | H8: 7.96 | I8: 14.56
D9: Infosys | E9: 12.03 | F9: 48966 | G9: 11.8 | H9: 9.49 | I9: 12.76
D10: TCS | E10: 2365.6 | F10: 8542000 | G10: 11.3 | H10: 10.6 | I10: 12.55
D12: Note: Market capitalization and share prices are based on the closing market price as of 31 July 2026. Forward EV/EBITDA and P/E trading multiples for the Indian peer companies have been sourced from publicly available market data for valuation benchmarking

Sheet CALANDARISATION
C2: CALANDARISATION OF EBITDA
B7: Note: | C7: Calendarisation Methodology: Trading comparables were valued as of 31 July 2026. EBITDA estimates were aligned to the calendar year ending December 2026. Companies with non-December fiscal year ends were calendarised using the 5/12 and 7/12 weighting approach, while companies with a 31 December fiscal year end required no calendarisation adjustment.
C11: PARTICULARS | D11: MICROSOFT (MSFT) | E11: ALPHABET (GOOGL) | F11: ORACLE (ORCL) | G11: SALESFORCE (CRM) | H11: IBM
C13: Valuation Date | D13: 46234 | E13: 46234 | F13: 46234 | G13: 46234 | H13: 46234
C14: FY End (as per comapany data) | D14: 46203 | E14: 46387 | F14: 46173 | G14: 46053 | H14: 46387
C15: FY27E EBITDA | D15: 240400 | E15: 296100 | F15: 49985 | G15: 17846 | H15: 21334
C16: FY28E EBITDA | D16: 299000 | E16: 382600 | F16: 71415 | G16: 19437 | H16: 22850
C17: FY29E EBITDA | D17: 377400 | E17: 472400 | F17: 103100 | G17: 21633 | H17: 24691
C18: Weight (Earlier FY) | D18: 5 | E18: Not Applicable | F18: 5 | G18: 5 | H18: Not Applicable
C19: Weight (Later FY) | D19: 7 | E19: Not Applicable | F19: 7 | G19: 7 | H19: Not Applicable
C20: Calendarised EBITDA (2026E) | D20: =((D15*D18)+(D16*D19))/12 -> 274583.33 | E20: =E15 -> 296100 | F20: =(F15*(F18/12))+(F16*(F19/12)) -> 62485.833 | G20: =(G15*(G18/12))+(G16*(G19/12)) -> 18774.083 | H20: =H15 -> 21334
C21: Calendarised EBITDA (2027E) | D21: =((D16*D18)+(D17*D19))/12 -> 344733.33 | E21: =E16 -> 382600 | F21: =((F16*F18)+(F17*F19))/12 -> 89897.917 | G21: =((G16*G18)+(G17*G19))/12 -> 20718 | H21: =H16 -> 22850

Sheet EV BRIDGE
D2: ENTERPRISE VALUE (EV) BRIDGE
D6: EV = MARKET CAP + DEBT + LEASES + PREFFERED STOCK + MI - CASH - INVESTMENTS
D9: EV Bridge Items | E9: MICROSOFT | F9: ALPHABET (GOOGL) | G9: ORACLE | H9: SALESFORCE | I9: IBM
D10: Market Capitalization | E10: ='US COMPANIES'!D8 -> 3677000 | F10: ='US COMPANIES'!D9 -> 4230000 | G10: ='US COMPANIES'!D10 -> 433569 | H10: ='US COMPANIES'!D11 -> 160696 | I10: ='US COMPANIES'!D12 -> 220761
D11: Add: Total Debt | E11: =9227+31067 -> 40294 | F11: 46547 | G11: 129541 | H11: 14439 | I11: 61260
D12: Add: Lease Liabilities | E12: =16532 -> 16532 | F12: 12744 | G12: 26648 | H12: 2737 | I12: 3347
D13: Add: Preferred Stock | E13: 0 | F13: 0 | G13: 4954 | H13: 0 | I13: 0
D14: Add: Minority Interest | E14: 0 | F14: 0 | G14: 548 | H14: 0 | I14: 93
D15: Less: Cash & Cash Equivalents | E15: =20935 -> 20935 | F15: 30708 | G15: 31289 | H15: 7327 | I15: 13587
D16: Less: Non-operating Investments | E16: =55908 -> 55908 | F16: 96135 | G16: 605 | H16: 2238 | I16: 10286
D17: Enterprise Value | E17: =E10+E11+E12+E13+E14-E15-E16 -> 3656983 | F17: =F10+F11+F12+F13+F14-F15-F16 -> 4162448 | G17: =G10+G11+G12+G13+G14-G15-G16 -> 563366 | H17: =H10+H11+H12+H13+H14-H15-H16 -> 168307 | I17: =I10+I11+I12+I13+I14-I15-I16 -> 261588
D19: Note: Enterprise Value has been derived using the latest balance sheet items and represents the total value of the operating business used for EV/EBITDA valuation.

Sheet FINAL COMPS
E2: FINAL COMPARABLE COMPANIES
E6: Country | F6: Company | G6: EV/EBITDA 2026E | H6: EV/EBITDA 2027E | I6: P/E
E7: USA | F7: Microsoft | G7: ='US COMPANIES'!H8 -> 13.318299 | H7: ='US COMPANIES'!I8 -> 10.60815 | I7: ='US COMPANIES'!J8 -> 25.71
E8: USA | F8: Alphabet | G8: ='US COMPANIES'!H9 -> 14.057575 | H8: ='US COMPANIES'!I9 -> 10.879373 | I8: ='US COMPANIES'!J9 -> 25.32
E9: USA | F9: Oracle | G9: ='US COMPANIES'!H10 -> 9.0158996 | H9: ='US COMPANIES'!I10 -> 6.2667303 | I9: ='US COMPANIES'!J10 -> 28.17
E10: USA | F10: Salesforce | G10: ='US COMPANIES'!H11 -> 8.9648585 | H10: ='US COMPANIES'!I11 -> 8.1237089 | I10: ='US COMPANIES'!J11 -> 13.4
E11: USA | F11: IBM | G11: ='US COMPANIES'!H12 -> 12.261554 | H11: ='US COMPANIES'!I12 -> 11.448053 | I11: ='US COMPANIES'!J12 -> 22.73
E12: India | F12: Wipro | G12: ='INDIAN COMPANIES'!G8 -> 8.9 | H12: ='INDIAN COMPANIES'!H8 -> 7.96 | I12: ='INDIAN COMPANIES'!I8 -> 14.56
E13: India | F13: Infosys | G13: ='INDIAN COMPANIES'!G9 -> 11.8 | H13: ='INDIAN COMPANIES'!H9 -> 9.49 | I13: ='INDIAN COMPANIES'!I9 -> 12.76
E14: India | F14: TCS | G14: ='INDIAN COMPANIES'!G10 -> 11.3 | H14: ='INDIAN COMPANIES'!H10 -> 10.6 | I14: ='INDIAN COMPANIES'!I10 -> 12.55
E16: Executive Summary: The final comparable company set consists of five US technology companies and three Indian IT peers. Forward EV/EBITDA and P/E trading multiples have been standardized to enable consistent valuation benchmarking across the peer group.

Sheet PEER STATISTICS
D2: PEER GROUP STATS
D6: Metric | E6: India | F6: USA | G6: Overall
D7: Average EV/EBITDA 2026E | E7: =AVERAGE('FINAL COMPS'!G12:G14) -> 10.666667 | F7: =AVERAGE('FINAL COMPS'!G7:G11) -> 11.523637 | G7: =AVERAGE('FINAL COMPS'!G7:G14) -> 11.202273
D8: Median EV/EBITDA 2026E | E8: =MEDIAN('FINAL COMPS'!G12:G14) -> 11.3 | F8: =MEDIAN('FINAL COMPS'!G7:G11) -> 12.261554 | G8: =MEDIAN('FINAL COMPS'!G7:G14) -> 11.55
D9: Average EV/EBITDA 2027E | E9: =AVERAGE('FINAL COMPS'!H12:H14) -> 9.35 | F9: =AVERAGE('FINAL COMPS'!H7:H11) -> 9.4652029 | G9: =AVERAGE('FINAL COMPS'!H7:H14) -> 9.4220018
D10: Median EV/EBITDA 2027E | E10: =MEDIAN('FINAL COMPS'!H12:H14) -> 9.49 | F10: =MEDIAN('FINAL COMPS'!H7:H11) -> 10.60815 | G10: =MEDIAN('FINAL COMPS'!H7:H14) -> 10.045
D11: Average P/E | E11: =AVERAGE('FINAL COMPS'!I12:I14) -> 13.29 | F11: =AVERAGE('FINAL COMPS'!I7:I11) -> 23.066 | G11: =AVERAGE('FINAL COMPS'!I7:I14) -> 19.4
D12: Median P/E | E12: =MEDIAN('FINAL COMPS'!I12:I14) -> 12.76 | F12: =MEDIAN('FINAL COMPS'!I7:I11) -> 25.32 | G12: =MEDIAN('FINAL COMPS'!I7:I14) -> 18.645

Sheet CHARTS
D3: VALUATION BENCHMARKING DASHBOARD
B10: 1) | Q10: 2)
E25: EV/EBITDA Comparison (2026E vs 2027E) chart | T25: P/E Comparison Chart
D27: Inference: Alphabet trades at the highest EV/EBITDA multiple in 2026E, followed closely by Microsoft. Oracle and Salesforce have the lowest valuation multiples, indicating relatively lower EBITDA-based valuations. Across all peers, EV/EBITDA declines in 2027E, reflecting expected EBITDA growth and multiple compression. | S27: Inference: Oracle trades at the highest P/E multiple (28.17×), followed by Microsoft (25.71×) and Alphabet (25.32×), reflecting a stronger valuation premium driven by higher earnings growth expectations. IBM is moderately valued at 22.73×, while Salesforce and the three Indian IT companies (Wipro, Infosys and TCS) trade in the 12.5×–14.6× range, indicating comparatively lower earnings-based valuations as compared to the other companies in the peer group.
B35: 3) | Q35: 4)
E50: EV/EBITDA Multiple Compression Analysis (2026E–2027E) | T50: Average Valuation Multiples: India vs USA
D52: The chart shows a decline in EV/EBITDA multiples from 2026E to 2027E across all peer companies, indicating that EBITDA is expected to grow faster than enterprise value. Alphabet (14.06×) and Microsoft (13.32×) remain the highest-valued companies in 2026E, reflecting their premium growth expectations, while Oracle records the sharpest multiple compression (9.02× to 6.27×), suggesting the strongest forecast improvement in operating earnings. | S52: The benchmark comparison shows that US technology companies trade at higher average valuation multiples than Indian IT peers, particularly on a P/E basis (23.07× vs 13.29×), reflecting a stronger earnings valuation premium. While the average EV/EBITDA multiple declines from 2026E to 2027E for both regions, the gap narrows in 2027E (9.47× for USA vs 9.35× for India), indicating relatively similar forward operating earnings growth expectations.
